aioudp/__init__.py
aioudp/client.py
aioudp/connection.py
aioudp/exceptions.py
aioudp/py.typed
aioudp/server.py
aioudp-2.0.0.dist-info/LICENSE.txt
aioudp-2.0.0.dist-info/METADATA
aioudp-2.0.0.dist-info/WHEEL
aioudp-2.0.0.dist-info/RECORD
