Metadata-Version: 2.1
Name: aioudp
Version: 2.0.0
Summary: A better API for asynchronous UDP
Home-page: https://github.com/ThatXliner/aioudp
License: GPL-3.0-or-later
Keywords: udp,asyncio
Author: Bryan Hu
Author-email: thatxliner@gmail.com
Requires-Python: >=3.8,<4.0
Classifier: Development Status :: 5 - Production/Stable
Classifier: License :: OSI Approved :: GNU General Public License v3 or later (GPLv3+)
Classifier: Natural Language :: English
Classifier: Operating System :: OS Independent
Classifier: Programming Language :: Python :: 3
Classifier: Programming Language :: Python :: 3.8
Classifier: Programming Language :: Python :: 3.9
Classifier: Programming Language :: Python :: 3.10
Classifier: Programming Language :: Python :: 3.11
Classifier: Programming Language :: Python :: 3.12
Classifier: Programming Language :: Python :: 3.13
Classifier: Programming Language :: Python :: Implementation :: CPython
Classifier: Typing :: Typed
Project-URL: Documentation, https://aioudp.readthedocs.io/en/latest/index.html
